bayesopt_openmdao/__init__.py
bayesopt_openmdao/bayesopt_optimizer.py
bayesopt_openmdao-0.1.dist-info/DESCRIPTION.rst
bayesopt_openmdao-0.1.dist-info/METADATA
bayesopt_openmdao-0.1.dist-info/RECORD
bayesopt_openmdao-0.1.dist-info/WHEEL
bayesopt_openmdao-0.1.dist-info/metadata.json
bayesopt_openmdao-0.1.dist-info/top_level.txt
