Metadata-Version: 2.0
Name: bayesopt-openmdao
Version: 0.1
Summary: UNKNOWN
Home-page: https://github.com/metamorph-inc/bayesopt_openmdao
Author: UNKNOWN
Author-email: UNKNOWN
License: UNKNOWN
Platform: UNKNOWN
Requires-Dist: bayesopt
Requires-Dist: openmdao (>=1.7.1)
